noises/__init__.py
noises-1.0.2.dist-info/LICENSE
noises-1.0.2.dist-info/METADATA
noises-1.0.2.dist-info/WHEEL
noises-1.0.2.dist-info/top_level.txt
noises-1.0.2.dist-info/RECORD
