Metadata-Version: 2.1
Name: noises
Version: 1.0.2
Summary: A package for generation Procedural Noises in Image form.
Home-page: https://escapedshadows.com/pythonlibs/noises.html
Author: EscapedShadows
Author-email: packages@escapedshadows.com
Classifier: Programming Language :: Python :: 3
Classifier: License :: OSI Approved :: Apache Software License
Classifier: Operating System :: OS Independent
Requires-Python: >=3.6
License-File: LICENSE
Requires-Dist: requests
Requires-Dist: urllib3
